file_search.py
file_search-0.0.3.dist-info/DESCRIPTION.rst
file_search-0.0.3.dist-info/METADATA
file_search-0.0.3.dist-info/RECORD
file_search-0.0.3.dist-info/WHEEL
file_search-0.0.3.dist-info/metadata.json
file_search-0.0.3.dist-info/top_level.txt
