Metadata-Version: 2.0
Name: file-search
Version: 0.0.3
Summary: search file more easily
Home-page: https://github.com/ismaan1998/file_search
Author: Indrajeet Singh
Author-email: indrajeetsinghmaan@gmail.com
License: UNKNOWN
Platform: UNKNOWN
Classifier: Programming Language :: Python :: 3
Classifier: Operating System :: OS Independent
